py100/__init__.py
py100/py100.py
py100-1.0.dist-info/METADATA
py100-1.0.dist-info/WHEEL
py100-1.0.dist-info/top_level.txt
py100-1.0.dist-info/RECORD
