Metadata-Version: 2.1
Name: py100
Version: 1.0
Summary: VT100 escape sequences wrapper
Home-page: https://github.com/pboardman/py100
Author: Pascal Boardman
Author-email: pascalboardman@gmail.com
License: MIT
Keywords: terminal DEC escape sequence wrapper
Platform: UNKNOWN
Classifier: Intended Audience :: End Users/Desktop
Classifier: License :: OSI Approved :: MIT License
Classifier: Programming Language :: Python :: 3
Classifier: Programming Language :: Python :: 3.3
Classifier: Programming Language :: Python :: 3.4
Classifier: Programming Language :: Python :: 3.5
